github_fetch_pullrequest/__init__.py
github_fetch_pullrequest/cmd.py
github_fetch_pullrequest-0.0.2.dist-info/LICENSE
github_fetch_pullrequest-0.0.2.dist-info/METADATA
github_fetch_pullrequest-0.0.2.dist-info/WHEEL
github_fetch_pullrequest-0.0.2.dist-info/entry_points.txt
github_fetch_pullrequest-0.0.2.dist-info/top_level.txt
github_fetch_pullrequest-0.0.2.dist-info/RECORD
