Metadata-Version: 2.1
Name: github-fetch-pullrequest
Version: 0.0.2
Summary: Script to pull request from GitHub.
Home-page: https://github.com/Josca/github-fetch-pullrequest
Author: Josef Hák
Author-email: jhak@redhat.com
License: GPLv2
Platform: UNKNOWN
Classifier: Programming Language :: Python :: 3
Classifier: License :: OSI Approved :: GNU General Public License v2 (GPLv2)
Classifier: Operating System :: OS Independent
Requires-Dist: simplejson (==3.16.0)
Requires-Dist: gitpython (==2.1.11)
